limedriver/limedriver.pyx
limedriver/limedriver.cpp
limedriver/__init__.py
limedriver/__main__.py
limedriver/binding.cpython-311-x86_64-linux-gnu.so
limedriver/hdf_reader.py
limedriver-0.4.0.dist-info/LICENSE
limedriver-0.4.0.dist-info/METADATA
limedriver-0.4.0.dist-info/RECORD
limedriver-0.4.0.dist-info/top_level.txt
limedriver-0.4.0.dist-info/WHEEL
limedriver.libs/libselinux-64a010fa.so.1
limedriver.libs/libpcre2-8-516f4c9d.so.0.7.1
limedriver.libs/libhdf5_hl_cpp-cfbde754.so.100.1.3
limedriver.libs/libhdf5-b5e70f84.so.103.1.0
limedriver.libs/libhdf5_hl-0b60eabd.so.100.1.2
limedriver.libs/libLimeSuite-848a7af5.so.23.11.0
limedriver.libs/libaec-91f0ca0f.so.0.0.8
limedriver.libs/libusb-1-1b307d35.0.so.0.2.0
limedriver.libs/libmount-a0fce023.so.1.1.0
limedriver.libs/libudev-6ca67360.so.1.6.11
limedriver.libs/libblkid-7ac37cd8.so.1.1.0
limedriver.libs/libuuid-48d6f845.so.1.3.0
limedriver.libs/libsz-0deeef7d.so.2.0.1
limedriver.libs/libhdf5_cpp-165bc8b8.so.103.1.0
