Metadata-Version: 2.1
Name: limedriver
Version: 0.4.0
Summary: Python bindings for limedriver
Author-email: Kumi <limedriver@kumi.email>
License: MIT License
Project-URL: Homepage, https://nqrduck.cool
Project-URL: Bug Tracker, https://github.com/nqrduck/limedriverbindings/issues
Project-URL: Source Code, https://github.com/nqrduck/limedriverbindings
Classifier: Development Status :: 4 - Beta
Classifier: Intended Audience :: Developers
Classifier: Topic :: Software Development :: Build Tools
Classifier: Programming Language :: Python :: 3
Requires-Python: >=3.10
License-File: LICENSE
Requires-Dist: h5py
